rainduck/__init__.py
rainduck/cli.py
rainduck/code_elements.py
rainduck/errors.py
rainduck/tokens.py
rainduck/transpiler.py
rainduck-0.5.0.dist-info/licenses/LICENSE
rainduck-0.5.0.dist-info/METADATA
rainduck-0.5.0.dist-info/WHEEL
rainduck-0.5.0.dist-info/entry_points.txt
rainduck-0.5.0.dist-info/top_level.txt
rainduck-0.5.0.dist-info/RECORD
