Metadata-Version: 2.4
Name: rainduck
Version: 0.5.0
Summary: A simple BrainFuck extension with macros
Author-email: Lukáš Koma <koma.luky@gmail.com>
License-Expression: MIT
Project-URL: Homepage, https://github.com/Skrret/rainduck
Project-URL: Issues, https://github.com/Skrret/rainduck/issues
Classifier: Programming Language :: Python :: 3
Classifier: Operating System :: OS Independent
Requires-Python: >=3.11
License-File: LICENSE
Requires-Dist: typer
Dynamic: license-file
